pipen_gcs.py
pipen_gcs-1.0.0.dist-info/METADATA
pipen_gcs-1.0.0.dist-info/WHEEL
pipen_gcs-1.0.0.dist-info/licenses/LICENSE
pipen_gcs-1.0.0.dist-info/RECORD
