Metadata-Version: 2.4
Name: pipen-gcs
Version: 1.0.0
Summary: A plugin for pipen to handle file metadata in Google Cloud Storage
License: MIT
License-File: LICENSE
Author: pwwang
Author-email: 1188067+pwwang@users.noreply.github.com
Requires-Python: >=3.9,<4.0
Classifier: License :: OSI Approved :: MIT License
Classifier: Programming Language :: Python :: 3
Classifier: Programming Language :: Python :: 3.9
Classifier: Programming Language :: Python :: 3.10
Classifier: Programming Language :: Python :: 3.11
Classifier: Programming Language :: Python :: 3.12
Classifier: Programming Language :: Python :: 3.13
Classifier: Programming Language :: Python :: 3.14
Requires-Dist: google-cloud-storage (>=3,<4)
Requires-Dist: pipen (>=1.0,<2.0)
